<?xml version="1.0" encoding="UTF-8"?>
<navigationModel
  ns = "http://schemas.android.com?import=com.android.tools.idea.editors.navigation.model.*">
  <locations  
    class = "java.util.ArrayList">
    <statePointEntry>
      <state      
        class = "com.android.tools.idea.editors.navigation.model.ActivityState"      
        className = "com.constantinnovationsinc.livemultimedia.activities.LiveMultimediaActivity"/>
      <point      
        x = "488"      
        y = "120"/>
    </statePointEntry>
    <statePointEntry>
      <state      
        class = "com.android.tools.idea.editors.navigation.model.MenuState"      
        className = "com.constantinnovationsinc.livemultimedia.activities.LiveMultimediaActivity"/>
      <point      
        x = "1756"      
        y = "120"/>
    </statePointEntry>
    <statePointEntry>
      <state      
        class = "com.android.tools.idea.editors.navigation.model.ActivityState"      
        className = "com.constantinnovationsinc.livemultimedia.activities.CameraDetailActivity"/>
      <point      
        x = "500"      
        y = "1480"/>
    </statePointEntry>
  </locations>
</navigationModel>
